pyauxm/__init__.py
pyauxm/pd_streamlib.py
pyauxm/pd_streamlib_patch.py
pyauxm/psql.py
pyauxm/twisted_aux.py
pyauxm/version.py
pyauxm/bin/__init__.py
pyauxm/bin/jsonbrowse.py
pyauxm/pp/__init__.py
pyauxm/pp/forkfun.py
pyauxm/pp/forkmap.py
pyauxm/pp/mp.py
pyauxm/pp/ppmap.py
pyauxm/pp/test_mp.py
pyauxm/zmq/__init__.py
pyauxm/zmq/zmqlogger.py
pyauxm-1.5.0.dist-info/METADATA
pyauxm-1.5.0.dist-info/WHEEL
pyauxm-1.5.0.dist-info/entry_points.txt
pyauxm-1.5.0.dist-info/top_level.txt
pyauxm-1.5.0.dist-info/RECORD
